encoder/src/encoder.v
module priority_encoder(clk,D,O);
  input [7:0] D;
  input clk;
  output reg [3:0] O;

  always@(posedge clk)
  begin
    if(D[7]) O = 3'b111;
    else if(D[6])O = 3'b110;   
    else if(D[5])O = 3'b101;
    else if(D[4])O = 3'b100;
    else if(D[3])O = 3'b011;
    else if(D[2])O = 3'b010;
    else if(D[1])O = 3'b001;
    else if(D[0])O = 3'b000;
    else O = 3'b000;
  end
endmodule

encoder/simulation/test_bench_pe.v
module tb_pe();
  reg clk;
  reg [7:0] d;
  wire [7:0] o;
  
  priority_encoder pe(clk,d,o);

  initial clk = 0;
  always #5 clk=~clk;
  initial
  begin
    for (int i=0; i<256; i=i+1) begin
            d = i;
            #10;
        end
    $finish;

  end
  
  initial begin
    $dumpfile("pe_tb.vcd");
    $dumpvars(0,tb_pe);
  end
  
endmodule

encoder/simulation/pe_tb.vcd
$date
	Sun Oct 27 22:59:05 2024
$end
$version
	Icarus Verilog
$end
$timescale
	1s
$end
$scope module tb_pe $end
$var wire 8 ! o [7:0] $end
$var reg 1 " clk $end
$var reg 8 # d [7:0] $end
$scope module pe $end
$var wire 8 $ D [7:0] $end
$var wire 1 " clk $end
$var reg 4 % O [3:0] $end
$upscope $end
$scope begin $ivl_for_loop0 $end
$var integer 32 & i [31:0] $end
$upscope $end
$upscope $end
$enddefinitions $end
#0
$dumpvars
b0 &
bx %
b0 $
b0 #
0"
b0xxxx !
$end
#5
b0 !
b0 %
1"
#10
0"
b1 #
b1 $
b1 &
#15
1"
#20
0"
b10 #
b10 $
b10 &
#25
b1 !
b1 %
1"
#30
0"
b11 #
b11 $
b11 &
#35
1"
#40
0"
b100 #
b100 $
b100 &
#45
b10 !
b10 %
1"
#50
0"
b101 #
b101 $
b101 &
#55
1"
#60
0"
b110 #
b110 $
b110 &
#65
1"
#70
0"
b111 #
b111 $
b111 &
#75
1"
#80
0"
b1000 #
b1000 $
b1000 &
#85
b11 !
b11 %
1"
#90
0"
b1001 #
b1001 $
b1001 &
#95
1"
#100
0"
b1010 #
b1010 $
b1010 &
#105
1"
#110
0"
b1011 #
b1011 $
b1011 &
#115
1"
#120
0"
b1100 #
b1100 $
b1100 &
#125
1"
#130
0"
b1101 #
b1101 $
b1101 &
#135
1"
#140
0"
b1110 #
b1110 $
b1110 &
#145
1"
#150
0"
b1111 #
b1111 $
b1111 &
#155
1"
#160
0"
b10000 #
b10000 $
b10000 &
#165
b100 !
b100 %
1"
#170
0"
b10001 #
b10001 $
b10001 &
#175
1"
#180
0"
b10010 #
b10010 $
b10010 &
#185
1"
#190
0"
b10011 #
b10011 $
b10011 &
#195
1"
#200
0"
b10100 #
b10100 $
b10100 &
#205
1"
#210
0"
b10101 #
b10101 $
b10101 &
#215
1"
#220
0"
b10110 #
b10110 $
b10110 &
#225
1"
#230
0"
b10111 #
b10111 $
b10111 &
#235
1"
#240
0"
b11000 #
b11000 $
b11000 &
#245
1"
#250
0"
b11001 #
b11001 $
b11001 &
#255
1"
#260
0"
b11010 #
b11010 $
b11010 &
#265
1"
#270
0"
b11011 #
b11011 $
b11011 &
#275
1"
#280
0"
b11100 #
b11100 $
b11100 &
#285
1"
#290
0"
b11101 #
b11101 $
b11101 &
#295
1"
#300
0"
b11110 #
b11110 $
b11110 &
#305
1"
#310
0"
b11111 #
b11111 $
b11111 &
#315
1"
#320
0"
b100000 #
b100000 $
b100000 &
#325
b101 !
b101 %
1"
#330
0"
b100001 #
b100001 $
b100001 &
#335
1"
#340
0"
b100010 #
b100010 $
b100010 &
#345
1"
#350
0"
b100011 #
b100011 $
b100011 &
#355
1"
#360
0"
b100100 #
b100100 $
b100100 &
#365
1"
#370
0"
b100101 #
b100101 $
b100101 &
#375
1"
#380
0"
b100110 #
b100110 $
b100110 &
#385
1"
#390
0"
b100111 #
b100111 $
b100111 &
#395
1"
#400
0"
b101000 #
b101000 $
b101000 &
#405
1"
#410
0"
b101001 #
b101001 $
b101001 &
#415
1"
#420
0"
b101010 #
b101010 $
b101010 &
#425
1"
#430
0"
b101011 #
b101011 $
b101011 &
#435
1"
#440
0"
b101100 #
b101100 $
b101100 &
#445
1"
#450
0"
b101101 #
b101101 $
b101101 &
#455
1"
#460
0"
b101110 #
b101110 $
b101110 &
#465
1"
#470
0"
b101111 #
b101111 $
b101111 &
#475
1"
#480
0"
b110000 #
b110000 $
b110000 &
#485
1"
#490
0"
b110001 #
b110001 $
b110001 &
#495
1"
#500
0"
b110010 #
b110010 $
b110010 &
#505
1"
#510
0"
b110011 #
b110011 $
b110011 &
#515
1"
#520
0"
b110100 #
b110100 $
b110100 &
#525
1"
#530
0"
b110101 #
b110101 $
b110101 &
#535
1"
#540
0"
b110110 #
b110110 $
b110110 &
#545
1"
#550
0"
b110111 #
b110111 $
b110111 &
#555
1"
#560
0"
b111000 #
b111000 $
b111000 &
#565
1"
#570
0"
b111001 #
b111001 $
b111001 &
#575
1"
#580
0"
b111010 #
b111010 $
b111010 &
#585
1"
#590
0"
b111011 #
b111011 $
b111011 &
#595
1"
#600
0"
b111100 #
b111100 $
b111100 &
#605
1"
#610
0"
b111101 #
b111101 $
b111101 &
#615
1"
#620
0"
b111110 #
b111110 $
b111110 &
#625
1"
#630
0"
b111111 #
b111111 $
b111111 &
#635
1"
#640
0"
b1000000 #
b1000000 $
b1000000 &
#645
b110 !
b110 %
1"
#650
0"
b1000001 #
b1000001 $
b1000001 &
#655
1"
#660
0"
b1000010 #
b1000010 $
b1000010 &
#665
1"
#670
0"
b1000011 #
b1000011 $
b1000011 &
#675
1"
#680
0"
b1000100 #
b1000100 $
b1000100 &
#685
1"
#690
0"
b1000101 #
b1000101 $
b1000101 &
#695
1"
#700
0"
b1000110 #
b1000110 $
b1000110 &
#705
1"
#710
0"
b1000111 #
b1000111 $
b1000111 &
#715
1"
#720
0"
b1001000 #
b1001000 $
b1001000 &
#725
1"
#730
0"
b1001001 #
b1001001 $
b1001001 &
#735
1"
#740
0"
b1001010 #
b1001010 $
b1001010 &
#745
1"
#750
0"
b1001011 #
b1001011 $
b1001011 &
#755
1"
#760
0"
b1001100 #
b1001100 $
b1001100 &
#765
1"
#770
0"
b1001101 #
b1001101 $
b1001101 &
#775
1"
#780
0"
b1001110 #
b1001110 $
b1001110 &
#785
1"
#790
0"
b1001111 #
b1001111 $
b1001111 &
#795
1"
#800
0"
b1010000 #
b1010000 $
b1010000 &
#805
1"
#810
0"
b1010001 #
b1010001 $
b1010001 &
#815
1"
#820
0"
b1010010 #
b1010010 $
b1010010 &
#825
1"
#830
0"
b1010011 #
b1010011 $
b1010011 &
#835
1"
#840
0"
b1010100 #
b1010100 $
b1010100 &
#845
1"
#850
0"
b1010101 #
b1010101 $
b1010101 &
#855
1"
#860
0"
b1010110 #
b1010110 $
b1010110 &
#865
1"
#870
0"
b1010111 #
b1010111 $
b1010111 &
#875
1"
#880
0"
b1011000 #
b1011000 $
b1011000 &
#885
1"
#890
0"
b1011001 #
b1011001 $
b1011001 &
#895
1"
#900
0"
b1011010 #
b1011010 $
b1011010 &
#905
1"
#910
0"
b1011011 #
b1011011 $
b1011011 &
#915
1"
#920
0"
b1011100 #
b1011100 $
b1011100 &
#925
1"
#930
0"
b1011101 #
b1011101 $
b1011101 &
#935
1"
#940
0"
b1011110 #
b1011110 $
b1011110 &
#945
1"
#950
0"
b1011111 #
b1011111 $
b1011111 &
#955
1"
#960
0"
b1100000 #
b1100000 $
b1100000 &
#965
1"
#970
0"
b1100001 #
b1100001 $
b1100001 &
#975
1"
#980
0"
b1100010 #
b1100010 $
b1100010 &
#985
1"
#990
0"
b1100011 #
b1100011 $
b1100011 &
#995
1"
#1000
0"
b1100100 #
b1100100 $
b1100100 &
#1005
1"
#1010
0"
b1100101 #
b1100101 $
b1100101 &
#1015
1"
#1020
0"
b1100110 #
b1100110 $
b1100110 &
#1025
1"
#1030
0"
b1100111 #
b1100111 $
b1100111 &
#1035
1"
#1040
0"
b1101000 #
b1101000 $
b1101000 &
#1045
1"
#1050
0"
b1101001 #
b1101001 $
b1101001 &
#1055
1"
#1060
0"
b1101010 #
b1101010 $
b1101010 &
#1065
1"
#1070
0"
b1101011 #
b1101011 $
b1101011 &
#1075
1"
#1080
0"
b1101100 #
b1101100 $
b1101100 &
#1085
1"
#1090
0"
b1101101 #
b1101101 $
b1101101 &
#1095
1"
#1100
0"
b1101110 #
b1101110 $
b1101110 &
#1105
1"
#1110
0"
b1101111 #
b1101111 $
b1101111 &
#1115
1"
#1120
0"
b1110000 #
b1110000 $
b1110000 &
#1125
1"
#1130
0"
b1110001 #
b1110001 $
b1110001 &
#1135
1"
#1140
0"
b1110010 #
b1110010 $
b1110010 &
#1145
1"
#1150
0"
b1110011 #
b1110011 $
b1110011 &
#1155
1"
#1160
0"
b1110100 #
b1110100 $
b1110100 &
#1165
1"
#1170
0"
b1110101 #
b1110101 $
b1110101 &
#1175
1"
#1180
0"
b1110110 #
b1110110 $
b1110110 &
#1185
1"
#1190
0"
b1110111 #
b1110111 $
b1110111 &
#1195
1"
#1200
0"
b1111000 #
b1111000 $
b1111000 &
#1205
1"
#1210
0"
b1111001 #
b1111001 $
b1111001 &
#1215
1"
#1220
0"
b1111010 #
b1111010 $
b1111010 &
#1225
1"
#1230
0"
b1111011 #
b1111011 $
b1111011 &
#1235
1"
#1240
0"
b1111100 #
b1111100 $
b1111100 &
#1245
1"
#1250
0"
b1111101 #
b1111101 $
b1111101 &
#1255
1"
#1260
0"
b1111110 #
b1111110 $
b1111110 &
#1265
1"
#1270
0"
b1111111 #
b1111111 $
b1111111 &
#1275
1"
#1280
0"
b10000000 #
b10000000 $
b10000000 &
#1285
b111 !
b111 %
1"
#1290
0"
b10000001 #
b10000001 $
b10000001 &
#1295
1"
#1300
0"
b10000010 #
b10000010 $
b10000010 &
#1305
1"
#1310
0"
b10000011 #
b10000011 $
b10000011 &
#1315
1"
#1320
0"
b10000100 #
b10000100 $
b10000100 &
#1325
1"
#1330
0"
b10000101 #
b10000101 $
b10000101 &
#1335
1"
#1340
0"
b10000110 #
b10000110 $
b10000110 &
#1345
1"
#1350
0"
b10000111 #
b10000111 $
b10000111 &
#1355
1"
#1360
0"
b10001000 #
b10001000 $
b10001000 &
#1365
1"
#1370
0"
b10001001 #
b10001001 $
b10001001 &
#1375
1"
#1380
0"
b10001010 #
b10001010 $
b10001010 &
#1385
1"
#1390
0"
b10001011 #
b10001011 $
b10001011 &
#1395
1"
#1400
0"
b10001100 #
b10001100 $
b10001100 &
#1405
1"
#1410
0"
b10001101 #
b10001101 $
b10001101 &
#1415
1"
#1420
0"
b10001110 #
b10001110 $
b10001110 &
#1425
1"
#1430
0"
b10001111 #
b10001111 $
b10001111 &
#1435
1"
#1440
0"
b10010000 #
b10010000 $
b10010000 &
#1445
1"
#1450
0"
b10010001 #
b10010001 $
b10010001 &
#1455
1"
#1460
0"
b10010010 #
b10010010 $
b10010010 &
#1465
1"
#1470
0"
b10010011 #
b10010011 $
b10010011 &
#1475
1"
#1480
0"
b10010100 #
b10010100 $
b10010100 &
#1485
1"
#1490
0"
b10010101 #
b10010101 $
b10010101 &
#1495
1"
#1500
0"
b10010110 #
b10010110 $
b10010110 &
#1505
1"
#1510
0"
b10010111 #
b10010111 $
b10010111 &
#1515
1"
#1520
0"
b10011000 #
b10011000 $
b10011000 &
#1525
1"
#1530
0"
b10011001 #
b10011001 $
b10011001 &
#1535
1"
#1540
0"
b10011010 #
b10011010 $
b10011010 &
#1545
1"
#1550
0"
b10011011 #
b10011011 $
b10011011 &
#1555
1"
#1560
0"
b10011100 #
b10011100 $
b10011100 &
#1565
1"
#1570
0"
b10011101 #
b10011101 $
b10011101 &
#1575
1"
#1580
0"
b10011110 #
b10011110 $
b10011110 &
#1585
1"
#1590
0"
b10011111 #
b10011111 $
b10011111 &
#1595
1"
#1600
0"
b10100000 #
b10100000 $
b10100000 &
#1605
1"
#1610
0"
b10100001 #
b10100001 $
b10100001 &
#1615
1"
#1620
0"
b10100010 #
b10100010 $
b10100010 &
#1625
1"
#1630
0"
b10100011 #
b10100011 $
b10100011 &
#1635
1"
#1640
0"
b10100100 #
b10100100 $
b10100100 &
#1645
1"
#1650
0"
b10100101 #
b10100101 $
b10100101 &
#1655
1"
#1660
0"
b10100110 #
b10100110 $
b10100110 &
#1665
1"
#1670
0"
b10100111 #
b10100111 $
b10100111 &
#1675
1"
#1680
0"
b10101000 #
b10101000 $
b10101000 &
#1685
1"
#1690
0"
b10101001 #
b10101001 $
b10101001 &
#1695
1"
#1700
0"
b10101010 #
b10101010 $
b10101010 &
#1705
1"
#1710
0"
b10101011 #
b10101011 $
b10101011 &
#1715
1"
#1720
0"
b10101100 #
b10101100 $
b10101100 &
#1725
1"
#1730
0"
b10101101 #
b10101101 $
b10101101 &
#1735
1"
#1740
0"
b10101110 #
b10101110 $
b10101110 &
#1745
1"
#1750
0"
b10101111 #
b10101111 $
b10101111 &
#1755
1"
#1760
0"
b10110000 #
b10110000 $
b10110000 &
#1765
1"
#1770
0"
b10110001 #
b10110001 $
b10110001 &
#1775
1"
#1780
0"
b10110010 #
b10110010 $
b10110010 &
#1785
1"
#1790
0"
b10110011 #
b10110011 $
b10110011 &
#1795
1"
#1800
0"
b10110100 #
b10110100 $
b10110100 &
#1805
1"
#1810
0"
b10110101 #
b10110101 $
b10110101 &
#1815
1"
#1820
0"
b10110110 #
b10110110 $
b10110110 &
#1825
1"
#1830
0"
b10110111 #
b10110111 $
b10110111 &
#1835
1"
#1840
0"
b10111000 #
b10111000 $
b10111000 &
#1845
1"
#1850
0"
b10111001 #
b10111001 $
b10111001 &
#1855
1"
#1860
0"
b10111010 #
b10111010 $
b10111010 &
#1865
1"
#1870
0"
b10111011 #
b10111011 $
b10111011 &
#1875
1"
#1880
0"
b10111100 #
b10111100 $
b10111100 &
#1885
1"
#1890
0"
b10111101 #
b10111101 $
b10111101 &
#1895
1"
#1900
0"
b10111110 #
b10111110 $
b10111110 &
#1905
1"
#1910
0"
b10111111 #
b10111111 $
b10111111 &
#1915
1"
#1920
0"
b11000000 #
b11000000 $
b11000000 &
#1925
1"
#1930
0"
b11000001 #
b11000001 $
b11000001 &
#1935
1"
#1940
0"
b11000010 #
b11000010 $
b11000010 &
#1945
1"
#1950
0"
b11000011 #
b11000011 $
b11000011 &
#1955
1"
#1960
0"
b11000100 #
b11000100 $
b11000100 &
#1965
1"
#1970
0"
b11000101 #
b11000101 $
b11000101 &
#1975
1"
#1980
0"
b11000110 #
b11000110 $
b11000110 &
#1985
1"
#1990
0"
b11000111 #
b11000111 $
b11000111 &
#1995
1"
#2000
0"
b11001000 #
b11001000 $
b11001000 &
#2005
1"
#2010
0"
b11001001 #
b11001001 $
b11001001 &
#2015
1"
#2020
0"
b11001010 #
b11001010 $
b11001010 &
#2025
1"
#2030
0"
b11001011 #
b11001011 $
b11001011 &
#2035
1"
#2040
0"
b11001100 #
b11001100 $
b11001100 &
#2045
1"
#2050
0"
b11001101 #
b11001101 $
b11001101 &
#2055
1"
#2060
0"
b11001110 #
b11001110 $
b11001110 &
#2065
1"
#2070
0"
b11001111 #
b11001111 $
b11001111 &
#2075
1"
#2080
0"
b11010000 #
b11010000 $
b11010000 &
#2085
1"
#2090
0"
b11010001 #
b11010001 $
b11010001 &
#2095
1"
#2100
0"
b11010010 #
b11010010 $
b11010010 &
#2105
1"
#2110
0"
b11010011 #
b11010011 $
b11010011 &
#2115
1"
#2120
0"
b11010100 #
b11010100 $
b11010100 &
#2125
1"
#2130
0"
b11010101 #
b11010101 $
b11010101 &
#2135
1"
#2140
0"
b11010110 #
b11010110 $
b11010110 &
#2145
1"
#2150
0"
b11010111 #
b11010111 $
b11010111 &
#2155
1"
#2160
0"
b11011000 #
b11011000 $
b11011000 &
#2165
1"
#2170
0"
b11011001 #
b11011001 $
b11011001 &
#2175
1"
#2180
0"
b11011010 #
b11011010 $
b11011010 &
#2185
1"
#2190
0"
b11011011 #
b11011011 $
b11011011 &
#2195
1"
#2200
0"
b11011100 #
b11011100 $
b11011100 &
#2205
1"
#2210
0"
b11011101 #
b11011101 $
b11011101 &
#2215
1"
#2220
0"
b11011110 #
b11011110 $
b11011110 &
#2225
1"
#2230
0"
b11011111 #
b11011111 $
b11011111 &
#2235
1"
#2240
0"
b11100000 #
b11100000 $
b11100000 &
#2245
1"
#2250
0"
b11100001 #
b11100001 $
b11100001 &
#2255
1"
#2260
0"
b11100010 #
b11100010 $
b11100010 &
#2265
1"
#2270
0"
b11100011 #
b11100011 $
b11100011 &
#2275
1"
#2280
0"
b11100100 #
b11100100 $
b11100100 &
#2285
1"
#2290
0"
b11100101 #
b11100101 $
b11100101 &
#2295
1"
#2300
0"
b11100110 #
b11100110 $
b11100110 &
#2305
1"
#2310
0"
b11100111 #
b11100111 $
b11100111 &
#2315
1"
#2320
0"
b11101000 #
b11101000 $
b11101000 &
#2325
1"
#2330
0"
b11101001 #
b11101001 $
b11101001 &
#2335
1"
#2340
0"
b11101010 #
b11101010 $
b11101010 &
#2345
1"
#2350
0"
b11101011 #
b11101011 $
b11101011 &
#2355
1"
#2360
0"
b11101100 #
b11101100 $
b11101100 &
#2365
1"
#2370
0"
b11101101 #
b11101101 $
b11101101 &
#2375
1"
#2380
0"
b11101110 #
b11101110 $
b11101110 &
#2385
1"
#2390
0"
b11101111 #
b11101111 $
b11101111 &
#2395
1"
#2400
0"
b11110000 #
b11110000 $
b11110000 &
#2405
1"
#2410
0"
b11110001 #
b11110001 $
b11110001 &
#2415
1"
#2420
0"
b11110010 #
b11110010 $
b11110010 &
#2425
1"
#2430
0"
b11110011 #
b11110011 $
b11110011 &
#2435
1"
#2440
0"
b11110100 #
b11110100 $
b11110100 &
#2445
1"
#2450
0"
b11110101 #
b11110101 $
b11110101 &
#2455
1"
#2460
0"
b11110110 #
b11110110 $
b11110110 &
#2465
1"
#2470
0"
b11110111 #
b11110111 $
b11110111 &
#2475
1"
#2480
0"
b11111000 #
b11111000 $
b11111000 &
#2485
1"
#2490
0"
b11111001 #
b11111001 $
b11111001 &
#2495
1"
#2500
0"
b11111010 #
b11111010 $
b11111010 &
#2505
1"
#2510
0"
b11111011 #
b11111011 $
b11111011 &
#2515
1"
#2520
0"
b11111100 #
b11111100 $
b11111100 &
#2525
1"
#2530
0"
b11111101 #
b11111101 $
b11111101 &
#2535
1"
#2540
0"
b11111110 #
b11111110 $
b11111110 &
#2545
1"
#2550
0"
b11111111 #
b11111111 $
b11111111 &
#2555
1"
#2560
0"
b100000000 &
